markers/__init__.py
markers/exceptions.py
markers/management/__init__.py
markers/management/commands/__init__.py
markers/management/commands/clean_markers.py
markers/models.py
markers/static/markers/fonts/DroidSans-Bold.ttf
markers/templatetags/__init__.py
markers/templatetags/markers.py
markers/urls.py
markers/views.py
django_markers-1.4.0.dist-info/LICENSE
django_markers-1.4.0.dist-info/METADATA
django_markers-1.4.0.dist-info/WHEEL
django_markers-1.4.0.dist-info/RECORD
