Metadata-Version: 2.1
Name: django-markers
Version: 1.4.0
Summary: Dynamic map marker generation using template images and arbitrary text
Home-page: https://github.com/danielquinn/django-markers
License: GPL-3.0-or-later
Author: Daniel Quinn
Author-email: code@danielquinn.org
Requires-Python: >=3.6,<4.0
Classifier: Development Status :: 4 - Beta
Classifier: Environment :: Web Environment
Classifier: Framework :: Django
Classifier: Intended Audience :: Developers
Classifier: License :: OSI Approved :: GNU General Public License v3 or later (GPLv3+)
Classifier: Operating System :: POSIX
Classifier: Operating System :: Unix
Classifier: Programming Language :: Python
Classifier: Programming Language :: Python :: 3
Classifier: Programming Language :: Python :: 3.6
Classifier: Programming Language :: Python :: 3.7
Classifier: Programming Language :: Python :: 3.8
Classifier: Programming Language :: Python :: 3.9
Classifier: Programming Language :: Python :: 3.10
Classifier: Programming Language :: Python :: 3.11
Classifier: Programming Language :: Python :: 2.6
Classifier: Programming Language :: Python :: 2.7
Classifier: Programming Language :: Python :: 3.5
Classifier: Programming Language :: Python :: 3.6
Classifier: Topic :: Internet :: WWW/HTTP
Classifier: Topic :: Internet :: WWW/HTTP :: Dynamic Content
Requires-Dist: django (>=3.2)
Requires-Dist: numpy (>=1.14.0,<2.0.0)
Requires-Dist: pillow (>=3.1.0)
Project-URL: Repository, https://github.com/danielquinn/django-markers
